cosima_core/__init__.py
cosima_core/communication_scenario.py
cosima_core/config.py
cosima_core/tutorial_scenario.py
cosima_core/messages/__init__.py
cosima_core/messages/message.proto
cosima_core/messages/message_pb2.py
cosima_core/results/result_1645085479.8887444.csv
cosima_core/simulators/__init__.py
cosima_core/simulators/collector.py
cosima_core/simulators/communication_simulator.py
cosima_core/simulators/ict_controller_simulator.py
cosima_core/simulators/omnetpp_connection.py
cosima_core/simulators/tic_toc_example/agent_simulator.py
cosima_core/simulators/tic_toc_example/content.csv
cosima_core/simulators/tic_toc_example/mosaik_csv.py
cosima_core/simulators/tutorial/simple_agent_simulator.py
cosima_core/util/build_omnet_project.py
cosima_core/util/run_by_command_line.txt
cosima_core/util/track_performance.py
cosima_core/util/util_functions.py
tests/__init__.py
tests/integration_tests/__init__.py
tests/integration_tests/scenarios.csv
tests/integration_tests/snapshot.txt
tests/integration_tests/test_all_scenarios.py
tests/integration_tests/update_snapshots.py
tests/unit_tests/__init__.py
tests/unit_tests/simulators/__init__.py
tests/unit_tests/simulators/test_communication_simulator.py
tests/unit_tests/simulators/tic_toc_example/__init__.py
tests/unit_tests/simulators/tic_toc_example/test_agent_simulator_tictoc.py
cosima-0.3.4.dist-info/LICENSE.txt
cosima-0.3.4.dist-info/METADATA
cosima-0.3.4.dist-info/WHEEL
cosima-0.3.4.dist-info/top_level.txt
cosima-0.3.4.dist-info/RECORD
