Metadata-Version: 2.1
Name: cosima
Version: 0.3.4
Summary: COmmunication SIMulation with Agents
Home-page: https://gitlab.com/mosaik/examples/cosima.git
Author: Cosima Team
Author-email: emilie.frost@offis.de
License: UNKNOWN
Platform: UNKNOWN
Classifier: Programming Language :: Python :: 3
Classifier: Operating System :: OS Independent
Classifier: License :: OSI Approved :: GNU Lesser General Public License v2 (LGPLv2)
Requires-Python: >=3.8
License-File: LICENSE.txt
Requires-Dist: arrow (==1.2.1)
Requires-Dist: matplotlib (==3.5.0)
Requires-Dist: mosaik (==3.0.0)
Requires-Dist: mosaik-api (==3.0.0)
Requires-Dist: numpy (==1.20.3)
Requires-Dist: pandas (==1.2.4)
Requires-Dist: protobuf (==3.20.1)
Requires-Dist: psutil (==5.9.0)
Requires-Dist: pytest (==6.2.5)
Requires-Dist: pytest-check (==1.0.5)
Requires-Dist: setuptools (==57.0.0)
Requires-Dist: simpy (==3.0.13)
Requires-Dist: termcolor (==1.1.0)
